{
  "paragraphs": [
    "M. Park vivait seul dans une petite maison au bout d'une rue tranquille.",
    "Un matin, sa fille lui apporta un cadeau. C'était un petit robot blanc aux yeux ronds et bleus.",
    "« Voici Pip, dit-elle. Il peut t'aider dans la maison. » M. Park n'était pas très convaincu par l'idée.",
    "« Je n'ai pas besoin d'un robot », dit-il. Mais il sourit poliment et dit merci.",
    "Le premier jour, Pip roula dans la cuisine. « Bonjour, dit-il. Voulez-vous un peu de thé ? »",
    "M. Park fut surpris. « Oui, s'il te plaît », répondit-il. Bientôt, le robot prépara une tasse de thé bien chaud.",
    "Chaque jour, Pip aidait un peu plus. Il allumait les lumières et lui rappelait de prendre ses médicaments.",
    "« C'est l'heure de vos comprimés, M. Park », disait-il gentiment. Le vieil homme se mit à apprécier son nouvel ami.",
    "Le soir, Pip lisait des histoires à voix haute. M. Park écoutait et fermait les yeux. La maison semblait moins vide à présent.",
    "Une nuit froide, M. Park glissa près de l'escalier. Il ne pouvait pas se relever tout seul.",
    "« Ne vous inquiétez pas, dit Pip. J'appelle votre fille tout de suite. » Les secours arrivèrent très vite.",
    "Après ce jour-là, M. Park fit entièrement confiance à Pip. Ils regardaient les informations et partageaient des matinées paisibles ensemble.",
    "« Tu n'es pas qu'une simple machine, dit-il un jour à Pip. Tu es une bonne compagnie. »",
    "Parfois, la bonne aide vient des endroits les plus inattendus."
  ],
  "glossary": {
    "the": { "pos": "article", "translation": "le, la, les" },
    "a": { "pos": "article", "translation": "un, une" },
    "mr": { "pos": "noun", "translation": "monsieur, M." },
    "live": { "pos": "verb", "translation": "vivre, habiter" },
    "alone": { "pos": "adverb", "translation": "seul" },
    "in": { "pos": "preposition", "translation": "dans, en" },
    "small": { "pos": "adjective", "translation": "petit" },
    "house": { "pos": "noun", "translation": "maison" },
    "at": { "pos": "preposition", "translation": "à, au" },
    "end": { "pos": "noun", "translation": "bout, fin" },
    "of": { "pos": "preposition", "translation": "de" },
    "quiet": { "pos": "adjective", "translation": "tranquille, silencieux" },
    "street": { "pos": "noun", "translation": "rue" },
    "one": { "pos": "numeral", "translation": "un" },
    "morning": { "pos": "noun", "translation": "matin" },
    "his": { "pos": "determiner", "translation": "son, sa, ses (à lui)" },
    "daughter": { "pos": "noun", "translation": "fille" },
    "bring": { "pos": "verb", "translation": "apporter" },
    "him": { "pos": "pronoun", "translation": "lui, le" },
    "gift": { "pos": "noun", "translation": "cadeau" },
    "it": { "pos": "pronoun", "translation": "il, ce, cela" },
    "be": { "pos": "verb", "translation": "être" },
    "was": { "pos": "verb", "translation": "était" },
    "white": { "pos": "adjective", "translation": "blanc" },
    "robot": { "pos": "noun", "translation": "robot" },
    "with": { "pos": "preposition", "translation": "avec, à" },
    "round": { "pos": "adjective", "translation": "rond" },
    "blue": { "pos": "adjective", "translation": "bleu" },
    "eye": { "pos": "noun", "translation": "œil" },
    "this": { "pos": "determiner", "translation": "ce, cet, cette, ceci" },
    "she": { "pos": "pronoun", "translation": "elle" },
    "say": { "pos": "verb", "translation": "dire" },
    "can": { "pos": "verb", "translation": "pouvoir" },
    "help": { "pos": "verb", "translation": "aider" },
    "you": { "pos": "pronoun", "translation": "tu, vous" },
    "around": { "pos": "preposition", "translation": "dans, autour de" },
    "not": { "pos": "adverb", "translation": "ne... pas" },
    "sure": { "pos": "adjective", "translation": "sûr, convaincu" },
    "about": { "pos": "preposition", "translation": "au sujet de, à propos de" },
    "idea": { "pos": "noun", "translation": "idée" },
    "i": { "pos": "pronoun", "translation": "je" },
    "do": { "pos": "verb", "translation": "faire (auxiliaire)" },
    "need": { "pos": "verb", "translation": "avoir besoin de" },
    "but": { "pos": "conjunction", "translation": "mais" },
    "he": { "pos": "pronoun", "translation": "il" },
    "smile": { "pos": "verb", "translation": "sourire" },
    "politely": { "pos": "adverb", "translation": "poliment, avec courtoisie" },
    "and": { "pos": "conjunction", "translation": "et" },
    "thank": { "pos": "noun", "translation": "merci" },
    "first": { "pos": "adjective", "translation": "premier" },
    "day": { "pos": "noun", "translation": "jour" },
    "roll": { "pos": "verb", "translation": "rouler" },
    "kitchen": { "pos": "noun", "translation": "cuisine" },
    "good": { "pos": "adjective", "translation": "bon" },
    "would": { "pos": "verb", "translation": "voudrais (conditionnel)" },
    "like": { "pos": "verb", "translation": "aimer, vouloir" },
    "some": { "pos": "determiner", "translation": "un peu de, du" },
    "tea": { "pos": "noun", "translation": "thé" },
    "surprised": { "pos": "adjective", "translation": "surpris" },
    "yes": { "pos": "interjection", "translation": "oui" },
    "please": { "pos": "adverb", "translation": "s'il te plaît, s'il vous plaît" },
    "answer": { "pos": "verb", "translation": "répondre" },
    "soon": { "pos": "adverb", "translation": "bientôt" },
    "make": { "pos": "verb", "translation": "faire, préparer" },
    "warm": { "pos": "adjective", "translation": "chaud, tiède" },
    "cup": { "pos": "noun", "translation": "tasse" },
    "every": { "pos": "determiner", "translation": "chaque, tous les" },
    "little": { "pos": "adverb", "translation": "peu" },
    "more": { "pos": "adverb", "translation": "plus" },
    "turn": { "pos": "verb", "translation": "allumer (turn on)" },
    "on": { "pos": "preposition", "translation": "sur, à" },
    "light": { "pos": "noun", "translation": "lumière" },
    "remind": { "pos": "verb", "translation": "rappeler (à quelqu'un)" },
    "to": { "pos": "preposition", "translation": "à, de" },
    "take": { "pos": "verb", "translation": "prendre" },
    "medicine": { "pos": "noun", "translation": "médicament, médecine" },
    "time": { "pos": "noun", "translation": "heure, temps" },
    "for": { "pos": "preposition", "translation": "pour, de" },
    "your": { "pos": "determiner", "translation": "ton, ta, votre" },
    "pill": { "pos": "noun", "translation": "comprimé, pilule" },
    "kindly": { "pos": "adverb", "translation": "gentiment, avec gentillesse" },
    "old": { "pos": "adjective", "translation": "vieux, âgé" },
    "man": { "pos": "noun", "translation": "homme" },
    "start": { "pos": "verb", "translation": "commencer, se mettre à" },
    "new": { "pos": "adjective", "translation": "nouveau, neuf" },
    "friend": { "pos": "noun", "translation": "ami" },
    "evening": { "pos": "noun", "translation": "soir, soirée" },
    "read": { "pos": "verb", "translation": "lire" },
    "story": { "pos": "noun", "translation": "histoire, conte" },
    "aloud": { "pos": "adverb", "translation": "à voix haute, à haute voix" },
    "listen": { "pos": "verb", "translation": "écouter" },
    "close": { "pos": "verb", "translation": "fermer" },
    "feel": { "pos": "verb", "translation": "se sentir, sembler" },
    "less": { "pos": "adverb", "translation": "moins" },
    "empty": { "pos": "adjective", "translation": "vide" },
    "now": { "pos": "adverb", "translation": "maintenant, à présent" },
    "cold": { "pos": "adjective", "translation": "froid" },
    "night": { "pos": "noun", "translation": "nuit" },
    "slip": { "pos": "verb", "translation": "glisser" },
    "near": { "pos": "preposition", "translation": "près de" },
    "stairs": { "pos": "noun", "translation": "escalier, escaliers" },
    "could": { "pos": "verb", "translation": "pouvait, pourrait" },
    "get": { "pos": "verb", "translation": "se relever (get up)" },
    "up": { "pos": "adverb", "translation": "en haut, debout" },
    "by": { "pos": "preposition", "translation": "par" },
    "himself": { "pos": "pronoun", "translation": "lui-même, tout seul" },
    "worry": { "pos": "verb", "translation": "s'inquiéter" },
    "call": { "pos": "verb", "translation": "appeler" },
    "arrive": { "pos": "verb", "translation": "arriver" },
    "very": { "pos": "adverb", "translation": "très" },
    "quickly": { "pos": "adverb", "translation": "vite, rapidement" },
    "after": { "pos": "preposition", "translation": "après" },
    "that": { "pos": "determiner", "translation": "ce, cet, cette, ce... là" },
    "trust": { "pos": "verb", "translation": "faire confiance, se fier" },
    "completely": { "pos": "adverb", "translation": "entièrement, complètement" },
    "they": { "pos": "pronoun", "translation": "ils, elles" },
    "watch": { "pos": "verb", "translation": "regarder" },
    "news": { "pos": "noun", "translation": "informations, nouvelles" },
    "share": { "pos": "verb", "translation": "partager" },
    "together": { "pos": "adverb", "translation": "ensemble" },
    "just": { "pos": "adverb", "translation": "seulement, juste" },
    "machine": { "pos": "noun", "translation": "machine" },
    "tell": { "pos": "verb", "translation": "dire, raconter" },
    "company": { "pos": "noun", "translation": "compagnie" },
    "sometimes": { "pos": "adverb", "translation": "parfois" },
    "right": { "pos": "adjective", "translation": "bon, juste, adéquat" },
    "come": { "pos": "verb", "translation": "venir" },
    "from": { "pos": "preposition", "translation": "de, depuis" },
    "most": { "pos": "adverb", "translation": "le plus (superlatif)" },
    "surprising": { "pos": "adjective", "translation": "inattendu, surprenant" },
    "place": { "pos": "noun", "translation": "endroit, lieu" }
  }
}
