{
  "the": { "pos": "article", "es": "el, la, los, las", "fr": "le, la, les", "pt": "o, a, os, as" },
  "a": { "pos": "article", "es": "un, una", "fr": "un, une", "pt": "um, uma" },
  "an": { "pos": "article", "es": "un, una", "fr": "un, une", "pt": "um, uma" },
  "this": { "pos": "determiner", "es": "este, esta, esto", "fr": "ce, cette", "pt": "este, esta, isto" },
  "that": { "pos": "determiner", "es": "ese, esa, eso; que", "fr": "ce, cette; que", "pt": "esse, essa, isso; que" },
  "these": { "pos": "determiner", "es": "estos, estas", "fr": "ces", "pt": "estes, estas" },
  "those": { "pos": "determiner", "es": "esos, esas", "fr": "ces", "pt": "esses, essas" },
  "some": { "pos": "determiner", "es": "algunos, algo de", "fr": "quelques, du", "pt": "alguns, algum" },
  "any": { "pos": "determiner", "es": "algún, cualquier", "fr": "n'importe quel, aucun", "pt": "algum, qualquer" },
  "each": { "pos": "determiner", "es": "cada", "fr": "chaque", "pt": "cada" },
  "every": { "pos": "determiner", "es": "cada, todo", "fr": "chaque, tout", "pt": "cada, todo" },
  "all": { "pos": "determiner", "es": "todo, todos", "fr": "tout, tous", "pt": "todo, todos" },
  "no": { "pos": "determiner", "es": "no, ningún", "fr": "non, aucun", "pt": "não, nenhum" },
  "both": { "pos": "determiner", "es": "ambos", "fr": "les deux", "pt": "ambos" },
  "much": { "pos": "determiner", "es": "mucho", "fr": "beaucoup", "pt": "muito" },
  "many": { "pos": "determiner", "es": "muchos", "fr": "beaucoup, nombreux", "pt": "muitos" },
  "more": { "pos": "determiner", "es": "más", "fr": "plus", "pt": "mais" },
  "most": { "pos": "determiner", "es": "la mayoría, más", "fr": "la plupart, le plus", "pt": "a maioria, mais" },
  "other": { "pos": "determiner", "es": "otro", "fr": "autre", "pt": "outro" },
  "another": { "pos": "determiner", "es": "otro", "fr": "un autre", "pt": "outro" },
  "such": { "pos": "determiner", "es": "tal, tan", "fr": "tel, un tel", "pt": "tal, tão" },
  "i": { "pos": "pronoun", "es": "yo", "fr": "je", "pt": "eu" },
  "you": { "pos": "pronoun", "es": "tú, usted, ustedes", "fr": "tu, vous", "pt": "tu, você, vocês" },
  "he": { "pos": "pronoun", "es": "él", "fr": "il", "pt": "ele" },
  "she": { "pos": "pronoun", "es": "ella", "fr": "elle", "pt": "ela" },
  "it": { "pos": "pronoun", "es": "ello, eso", "fr": "il, elle, ça", "pt": "ele, ela, isso" },
  "we": { "pos": "pronoun", "es": "nosotros", "fr": "nous", "pt": "nós" },
  "they": { "pos": "pronoun", "es": "ellos, ellas", "fr": "ils, elles", "pt": "eles, elas" },
  "me": { "pos": "pronoun", "es": "me, mí", "fr": "me, moi", "pt": "me, mim" },
  "him": { "pos": "pronoun", "es": "lo, le, él", "fr": "le, lui", "pt": "o, lhe, ele" },
  "her": { "pos": "pronoun", "es": "la, le, su; ella", "fr": "la, lui, son; elle", "pt": "a, lhe, dela; ela" },
  "us": { "pos": "pronoun", "es": "nos, nosotros", "fr": "nous", "pt": "nos, nós" },
  "them": { "pos": "pronoun", "es": "los, las, les; ellos", "fr": "les, eux", "pt": "os, as, lhes; eles" },
  "my": { "pos": "determiner", "es": "mi, mis", "fr": "mon, ma, mes", "pt": "meu, minha" },
  "your": { "pos": "determiner", "es": "tu, su", "fr": "ton, ta, votre", "pt": "teu, seu" },
  "his": { "pos": "determiner", "es": "su, sus (de él)", "fr": "son, sa, ses", "pt": "seu, dele" },
  "its": { "pos": "determiner", "es": "su (de ello)", "fr": "son, sa, ses", "pt": "seu, sua" },
  "our": { "pos": "determiner", "es": "nuestro", "fr": "notre, nos", "pt": "nosso" },
  "their": { "pos": "determiner", "es": "su, sus (de ellos)", "fr": "leur, leurs", "pt": "seu, deles" },
  "mine": { "pos": "pronoun", "es": "mío", "fr": "le mien", "pt": "meu, o meu" },
  "yours": { "pos": "pronoun", "es": "tuyo, suyo", "fr": "le tien, le vôtre", "pt": "teu, seu" },
  "who": { "pos": "pronoun", "es": "quién, que", "fr": "qui", "pt": "quem, que" },
  "whom": { "pos": "pronoun", "es": "a quién", "fr": "qui, à qui", "pt": "quem, a quem" },
  "whose": { "pos": "pronoun", "es": "de quién, cuyo", "fr": "dont, à qui", "pt": "de quem, cujo" },
  "which": { "pos": "pronoun", "es": "cuál, que", "fr": "quel, lequel", "pt": "qual, que" },
  "what": { "pos": "pronoun", "es": "qué, lo que", "fr": "quoi, que, quel", "pt": "que, o que" },
  "someone": { "pos": "pronoun", "es": "alguien", "fr": "quelqu'un", "pt": "alguém" },
  "something": { "pos": "pronoun", "es": "algo", "fr": "quelque chose", "pt": "algo, alguma coisa" },
  "anyone": { "pos": "pronoun", "es": "alguien, cualquiera", "fr": "n'importe qui, quelqu'un", "pt": "alguém, qualquer um" },
  "anything": { "pos": "pronoun", "es": "algo, cualquier cosa", "fr": "n'importe quoi, quelque chose", "pt": "qualquer coisa, algo" },
  "nobody": { "pos": "pronoun", "es": "nadie", "fr": "personne", "pt": "ninguém" },
  "nothing": { "pos": "pronoun", "es": "nada", "fr": "rien", "pt": "nada" },
  "everyone": { "pos": "pronoun", "es": "todos, todo el mundo", "fr": "tout le monde", "pt": "todos, toda a gente" },
  "everything": { "pos": "pronoun", "es": "todo", "fr": "tout", "pt": "tudo" },
  "himself": { "pos": "pronoun", "es": "él mismo, se", "fr": "lui-même, se", "pt": "ele mesmo, se" },
  "herself": { "pos": "pronoun", "es": "ella misma, se", "fr": "elle-même, se", "pt": "ela mesma, se" },
  "itself": { "pos": "pronoun", "es": "sí mismo, se", "fr": "lui-même, se", "pt": "si mesmo, se" },
  "themselves": { "pos": "pronoun", "es": "ellos mismos, se", "fr": "eux-mêmes, se", "pt": "eles mesmos, se" },
  "of": { "pos": "preposition", "es": "de", "fr": "de", "pt": "de" },
  "to": { "pos": "preposition", "es": "a, para", "fr": "à, vers", "pt": "a, para" },
  "in": { "pos": "preposition", "es": "en, dentro de", "fr": "dans, en", "pt": "em, dentro de" },
  "on": { "pos": "preposition", "es": "en, sobre", "fr": "sur", "pt": "em, sobre" },
  "at": { "pos": "preposition", "es": "en, a", "fr": "à, chez", "pt": "em, a" },
  "for": { "pos": "preposition", "es": "para, por", "fr": "pour", "pt": "para, por" },
  "with": { "pos": "preposition", "es": "con", "fr": "avec", "pt": "com" },
  "from": { "pos": "preposition", "es": "de, desde", "fr": "de, depuis", "pt": "de, desde" },
  "by": { "pos": "preposition", "es": "por, junto a", "fr": "par, près de", "pt": "por, junto a" },
  "about": { "pos": "preposition", "es": "sobre, acerca de", "fr": "à propos de, environ", "pt": "sobre, acerca de" },
  "as": { "pos": "preposition", "es": "como, mientras", "fr": "comme, en tant que", "pt": "como, à medida que" },
  "into": { "pos": "preposition", "es": "en, dentro de, hacia", "fr": "dans, vers", "pt": "para dentro de, em" },
  "over": { "pos": "preposition", "es": "sobre, encima de", "fr": "au-dessus de, par-dessus", "pt": "sobre, por cima de" },
  "under": { "pos": "preposition", "es": "bajo, debajo de", "fr": "sous", "pt": "sob, debaixo de" },
  "between": { "pos": "preposition", "es": "entre", "fr": "entre", "pt": "entre" },
  "through": { "pos": "preposition", "es": "a través de, por", "fr": "à travers, par", "pt": "através de, por" },
  "after": { "pos": "preposition", "es": "después de", "fr": "après", "pt": "depois de" },
  "before": { "pos": "preposition", "es": "antes de", "fr": "avant", "pt": "antes de" },
  "during": { "pos": "preposition", "es": "durante", "fr": "pendant", "pt": "durante" },
  "without": { "pos": "preposition", "es": "sin", "fr": "sans", "pt": "sem" },
  "within": { "pos": "preposition", "es": "dentro de", "fr": "à l'intérieur de", "pt": "dentro de" },
  "around": { "pos": "preposition", "es": "alrededor de", "fr": "autour de", "pt": "ao redor de, à volta de" },
  "against": { "pos": "preposition", "es": "contra", "fr": "contre", "pt": "contra" },
  "near": { "pos": "preposition", "es": "cerca de", "fr": "près de", "pt": "perto de" },
  "up": { "pos": "adverb", "es": "arriba, hacia arriba", "fr": "en haut, vers le haut", "pt": "para cima, acima" },
  "down": { "pos": "adverb", "es": "abajo, hacia abajo", "fr": "en bas, vers le bas", "pt": "para baixo, abaixo" },
  "out": { "pos": "adverb", "es": "fuera, afuera", "fr": "dehors, hors", "pt": "fora, para fora" },
  "off": { "pos": "adverb", "es": "fuera, apagado", "fr": "éteint, hors de", "pt": "desligado, fora" },
  "and": { "pos": "conjunction", "es": "y", "fr": "et", "pt": "e" },
  "but": { "pos": "conjunction", "es": "pero", "fr": "mais", "pt": "mas" },
  "or": { "pos": "conjunction", "es": "o", "fr": "ou", "pt": "ou" },
  "so": { "pos": "conjunction", "es": "así que, entonces", "fr": "donc, alors", "pt": "então, por isso" },
  "because": { "pos": "conjunction", "es": "porque", "fr": "parce que", "pt": "porque" },
  "if": { "pos": "conjunction", "es": "si", "fr": "si", "pt": "se" },
  "when": { "pos": "conjunction", "es": "cuando", "fr": "quand, lorsque", "pt": "quando" },
  "while": { "pos": "conjunction", "es": "mientras", "fr": "pendant que, tandis que", "pt": "enquanto" },
  "although": { "pos": "conjunction", "es": "aunque", "fr": "bien que", "pt": "embora" },
  "though": { "pos": "conjunction", "es": "aunque", "fr": "bien que, quoique", "pt": "embora, ainda que" },
  "since": { "pos": "conjunction", "es": "desde que, ya que", "fr": "depuis que, puisque", "pt": "desde que, já que" },
  "until": { "pos": "conjunction", "es": "hasta que", "fr": "jusqu'à ce que", "pt": "até que" },
  "unless": { "pos": "conjunction", "es": "a menos que", "fr": "à moins que", "pt": "a menos que" },
  "than": { "pos": "conjunction", "es": "que (comparativo)", "fr": "que (comparatif)", "pt": "do que" },
  "whether": { "pos": "conjunction", "es": "si, ya sea", "fr": "si, que", "pt": "se, quer" },
  "nor": { "pos": "conjunction", "es": "ni", "fr": "ni", "pt": "nem" },
  "yet": { "pos": "conjunction", "es": "sin embargo, aún", "fr": "pourtant, encore", "pt": "contudo, ainda" },
  "be": { "pos": "verb", "es": "ser, estar", "fr": "être", "pt": "ser, estar" },
  "am": { "pos": "verb", "es": "soy, estoy", "fr": "suis", "pt": "sou, estou" },
  "is": { "pos": "verb", "es": "es, está", "fr": "est", "pt": "é, está" },
  "are": { "pos": "verb", "es": "son, están, eres", "fr": "es, êtes, sont", "pt": "és, são, estão" },
  "was": { "pos": "verb", "es": "era, fue, estaba", "fr": "était, étais", "pt": "era, foi, estava" },
  "were": { "pos": "verb", "es": "eran, fueron, estaban", "fr": "étaient, étiez", "pt": "eram, foram, estavam" },
  "been": { "pos": "verb", "es": "sido, estado", "fr": "été", "pt": "sido, estado" },
  "being": { "pos": "verb", "es": "siendo, estando", "fr": "étant", "pt": "sendo, estando" },
  "have": { "pos": "verb", "es": "tener, haber", "fr": "avoir", "pt": "ter, haver" },
  "has": { "pos": "verb", "es": "tiene, ha", "fr": "a", "pt": "tem, há" },
  "had": { "pos": "verb", "es": "tenía, tuvo, había", "fr": "avait, avais", "pt": "tinha, teve, havia" },
  "do": { "pos": "verb", "es": "hacer", "fr": "faire", "pt": "fazer" },
  "does": { "pos": "verb", "es": "hace", "fr": "fait", "pt": "faz" },
  "did": { "pos": "verb", "es": "hizo, hacía", "fr": "fit, faisait", "pt": "fez, fazia" },
  "will": { "pos": "verb", "es": "(futuro), querrá", "fr": "(futur)", "pt": "(futuro)" },
  "would": { "pos": "verb", "es": "(condicional), haría", "fr": "(conditionnel)", "pt": "(condicional)" },
  "shall": { "pos": "verb", "es": "(futuro, deber)", "fr": "(futur, devoir)", "pt": "(futuro, dever)" },
  "should": { "pos": "verb", "es": "debería", "fr": "devrait", "pt": "deveria" },
  "can": { "pos": "verb", "es": "poder", "fr": "pouvoir", "pt": "poder" },
  "could": { "pos": "verb", "es": "podría, podía", "fr": "pourrait, pouvait", "pt": "poderia, podia" },
  "may": { "pos": "verb", "es": "poder, quizás", "fr": "pouvoir, peut-être", "pt": "poder, talvez" },
  "might": { "pos": "verb", "es": "podría, quizás", "fr": "pourrait, peut-être", "pt": "poderia, talvez" },
  "must": { "pos": "verb", "es": "deber, tener que", "fr": "devoir, falloir", "pt": "dever, ter que" },
  "get": { "pos": "verb", "es": "obtener, conseguir", "fr": "obtenir, avoir", "pt": "obter, conseguir" },
  "go": { "pos": "verb", "es": "ir", "fr": "aller", "pt": "ir" },
  "make": { "pos": "verb", "es": "hacer", "fr": "faire", "pt": "fazer" },
  "take": { "pos": "verb", "es": "tomar, llevar", "fr": "prendre", "pt": "tomar, levar" },
  "come": { "pos": "verb", "es": "venir", "fr": "venir", "pt": "vir" },
  "see": { "pos": "verb", "es": "ver", "fr": "voir", "pt": "ver" },
  "know": { "pos": "verb", "es": "saber, conocer", "fr": "savoir, connaître", "pt": "saber, conhecer" },
  "say": { "pos": "verb", "es": "decir", "fr": "dire", "pt": "dizer" },
  "think": { "pos": "verb", "es": "pensar", "fr": "penser", "pt": "pensar" },
  "want": { "pos": "verb", "es": "querer", "fr": "vouloir", "pt": "querer" },
  "need": { "pos": "verb", "es": "necesitar", "fr": "avoir besoin de", "pt": "precisar" },
  "like": { "pos": "verb", "es": "gustar; como", "fr": "aimer; comme", "pt": "gostar; como" },
  "look": { "pos": "verb", "es": "mirar, parecer", "fr": "regarder, sembler", "pt": "olhar, parecer" },
  "feel": { "pos": "verb", "es": "sentir", "fr": "sentir, ressentir", "pt": "sentir" },
  "run": { "pos": "verb", "es": "correr", "fr": "courir", "pt": "correr" },
  "give": { "pos": "verb", "es": "dar", "fr": "donner", "pt": "dar" },
  "find": { "pos": "verb", "es": "encontrar", "fr": "trouver", "pt": "encontrar" },
  "tell": { "pos": "verb", "es": "decir, contar", "fr": "dire, raconter", "pt": "dizer, contar" },
  "ask": { "pos": "verb", "es": "preguntar, pedir", "fr": "demander", "pt": "perguntar, pedir" },
  "not": { "pos": "adverb", "es": "no", "fr": "ne... pas", "pt": "não" },
  "very": { "pos": "adverb", "es": "muy", "fr": "très", "pt": "muito" },
  "too": { "pos": "adverb", "es": "demasiado, también", "fr": "trop, aussi", "pt": "demasiado, também" },
  "also": { "pos": "adverb", "es": "también", "fr": "aussi", "pt": "também" },
  "just": { "pos": "adverb", "es": "justo, solo, recién", "fr": "juste, seulement", "pt": "apenas, justo, já" },
  "only": { "pos": "adverb", "es": "solo, únicamente", "fr": "seulement, ne... que", "pt": "só, apenas" },
  "even": { "pos": "adverb", "es": "incluso, aún", "fr": "même", "pt": "até, mesmo" },
  "still": { "pos": "adverb", "es": "todavía, aún", "fr": "encore, toujours", "pt": "ainda" },
  "again": { "pos": "adverb", "es": "otra vez, de nuevo", "fr": "encore, de nouveau", "pt": "de novo, outra vez" },
  "now": { "pos": "adverb", "es": "ahora", "fr": "maintenant", "pt": "agora" },
  "then": { "pos": "adverb", "es": "entonces, luego", "fr": "alors, puis", "pt": "então, depois" },
  "here": { "pos": "adverb", "es": "aquí", "fr": "ici", "pt": "aqui" },
  "there": { "pos": "adverb", "es": "allí, ahí", "fr": "là, là-bas", "pt": "ali, lá" },
  "always": { "pos": "adverb", "es": "siempre", "fr": "toujours", "pt": "sempre" },
  "never": { "pos": "adverb", "es": "nunca", "fr": "jamais", "pt": "nunca" },
  "often": { "pos": "adverb", "es": "a menudo", "fr": "souvent", "pt": "frequentemente" },
  "sometimes": { "pos": "adverb", "es": "a veces", "fr": "parfois", "pt": "às vezes" },
  "soon": { "pos": "adverb", "es": "pronto", "fr": "bientôt", "pt": "em breve, cedo" },
  "well": { "pos": "adverb", "es": "bien", "fr": "bien", "pt": "bem" },
  "yes": { "pos": "interjection", "es": "sí", "fr": "oui", "pt": "sim" },
  "please": { "pos": "adverb", "es": "por favor", "fr": "s'il vous plaît", "pt": "por favor" },
  "thank": { "pos": "verb", "es": "agradecer, gracias", "fr": "remercier, merci", "pt": "agradecer, obrigado" },
  "today": { "pos": "adverb", "es": "hoy", "fr": "aujourd'hui", "pt": "hoje" },
  "tomorrow": { "pos": "adverb", "es": "mañana", "fr": "demain", "pt": "amanhã" },
  "yesterday": { "pos": "adverb", "es": "ayer", "fr": "hier", "pt": "ontem" },
  "good": { "pos": "adjective", "es": "bueno", "fr": "bon", "pt": "bom" },
  "new": { "pos": "adjective", "es": "nuevo", "fr": "nouveau", "pt": "novo" },
  "first": { "pos": "adjective", "es": "primero", "fr": "premier", "pt": "primeiro" },
  "last": { "pos": "adjective", "es": "último", "fr": "dernier", "pt": "último" },
  "long": { "pos": "adjective", "es": "largo", "fr": "long", "pt": "longo, comprido" },
  "little": { "pos": "adjective", "es": "pequeño, poco", "fr": "petit, peu", "pt": "pequeno, pouco" },
  "own": { "pos": "adjective", "es": "propio", "fr": "propre", "pt": "próprio" },
  "time": { "pos": "noun", "es": "tiempo, vez", "fr": "temps, fois", "pt": "tempo, vez" },
  "day": { "pos": "noun", "es": "día", "fr": "jour", "pt": "dia" },
  "thing": { "pos": "noun", "es": "cosa", "fr": "chose", "pt": "coisa" },
  "way": { "pos": "noun", "es": "manera, camino", "fr": "manière, chemin", "pt": "maneira, caminho" },
  "one": { "pos": "numeral", "es": "uno", "fr": "un", "pt": "um" },
  "two": { "pos": "numeral", "es": "dos", "fr": "deux", "pt": "dois" },
  "three": { "pos": "numeral", "es": "tres", "fr": "trois", "pt": "três" }
}
